{
  "version": "5.0.1",
  "flags": {},
  "shapes": [
    {
      "label": "not_pikachu",
      "points": [
        [
          45,
          19
        ],
        [
          119.93,
          19
        ],
        [
          119.93,
          98.96
        ],
        [
          45,
          98.96
        ]
      ],
      "group_id": null,
      "shape_type": "rectangle",
      "flags": {}
    }
  ],
  "imagePath": "not_pikachu_00108_jpg.rf.d9353f117f122007fa2cca51c289c0e5.jpg",
  "imageData": null,
  "imageHeight": 120,
  "imageWidth": 120
}